diffrays/__init__.py
diffrays/analyzer.py
diffrays/cli.py
diffrays/database.py
diffrays/explorer.py
diffrays/file_downloader.py
diffrays/log.py
diffrays/server.py
diffrays/static/images/logo-dark.png
diffrays/static/images/logo-light.png
diffrays/templates/base.html
diffrays/templates/dashboard.html
diffrays/templates/diff.html
diffrays/templates/index.html
diffrays/templates/list.html
diffrays/templates/raw.html
diffrays-1.5.dist-info/LICENSE
diffrays-1.5.dist-info/METADATA
diffrays-1.5.dist-info/WHEEL
diffrays-1.5.dist-info/entry_points.txt
diffrays-1.5.dist-info/top_level.txt
diffrays-1.5.dist-info/RECORD
