Metadata-Version: 2.1
Name: diffrays
Version: 1.5
Summary: Binary Diff Analysis Tool - Decompile, Compare, and Visualize Binary Changes
Author-email: Nikhil John Thomas <nikhiljohn2104@gmail.com>, Ayushman Dubey <ayushmandubey611@gmail.com>
License: MIT
Project-URL: Homepage, https://github.com/pwnfuzz/diffrays
Project-URL: Documentation, https://github.com/pwnfuzz/diffrays#readme
Project-URL: Repository, https://github.com/pwnfuzz/diffrays
Project-URL: Issues, https://github.com/pwnfuzz/diffrays/issues
Requires-Python: >=3.8
License-File: LICENSE
Requires-Dist: flask>=2.0.0
Requires-Dist: tqdm>=4.60.0
Requires-Dist: ida-domain>=0.1.0
Requires-Dist: requests
